pyflct/_flct.cpython-312-x86_64-linux-gnu.so
pyflct/flct.py
pyflct/_version.py
pyflct/flct.pyx
pyflct/utils.py
pyflct/sunkit.c
pyflct/_compiler.c
pyflct/sunkit.h
pyflct/version.py
pyflct/compiler_version.cpython-312-x86_64-linux-gnu.so
pyflct/setup_package.py
pyflct/__init__.py
pyflct/tests/test_flct.py
pyflct/tests/test_utils.py
pyflct/tests/__init__.py
pyflct/data/README.rst
pyflct/data/__init__.py
pyflct/data/test/testgauss_vy.csv
pyflct/data/test/hashgauss_F1.csv
pyflct/data/test/hashgauss_F2.csv
pyflct/data/test/testgauss_vm.csv
pyflct/data/test/IDL.txt
pyflct/data/test/testgaussvel.dat
pyflct/data/test/hashgauss.dat
pyflct/data/test/testgauss_vx.csv
pyflct/data/test/__init__.py
pyflct.libs/libfftw3-6b983104.so.3.5.5
pyflct-0.3.1.dist-info/WHEEL
pyflct-0.3.1.dist-info/top_level.txt
pyflct-0.3.1.dist-info/LICENSE.rst
pyflct-0.3.1.dist-info/RECORD
pyflct-0.3.1.dist-info/METADATA
