Metadata-Version: 2.1
Name: pyflct
Version: 0.3.1
Summary: A Python wrapper for Fourier Local Correlation Tracking.
Home-page: https://docs.sunpy.org/projects/pyflct/
Author: The SunPy Developers
Author-email: sunpy@googlegroups.com
License: LGPLv2+
Classifier: Development Status :: 5 - Production/Stable
Classifier: Intended Audience :: Science/Research
Classifier: License :: OSI Approved :: GNU Lesser General Public License v2 or later (LGPLv2+)
Classifier: Natural Language :: English
Classifier: Operating System :: MacOS
Classifier: Operating System :: POSIX :: Linux
Classifier: Operating System :: Microsoft :: Windows
Classifier: Programming Language :: Python
Classifier: Programming Language :: Python :: 3
Classifier: Programming Language :: Python :: 3.10
Classifier: Programming Language :: Python :: 3.11
Classifier: Programming Language :: Python :: 3.12
Classifier: Topic :: Scientific/Engineering :: Physics
Requires-Python: >=3.10
License-File: LICENSE.rst
Requires-Dist: numpy
Requires-Dist: packaging
Provides-Extra: all
Requires-Dist: pytest-astropy ; extra == 'all'
Provides-Extra: dev
Requires-Dist: pytest-astropy ; extra == 'dev'
Requires-Dist: matplotlib ; extra == 'dev'
Requires-Dist: sphinx ; extra == 'dev'
Requires-Dist: sphinx-automodapi ; extra == 'dev'
Requires-Dist: sphinx-changelog ; extra == 'dev'
Requires-Dist: sphinx-gallery ; extra == 'dev'
Requires-Dist: sunpy-sphinx-theme ; extra == 'dev'
Provides-Extra: docs
Requires-Dist: matplotlib ; extra == 'docs'
Requires-Dist: sphinx ; extra == 'docs'
Requires-Dist: sphinx-automodapi ; extra == 'docs'
Requires-Dist: sphinx-changelog ; extra == 'docs'
Requires-Dist: sphinx-gallery ; extra == 'docs'
Requires-Dist: sunpy-sphinx-theme ; extra == 'docs'
Provides-Extra: test
Requires-Dist: pytest-astropy ; extra == 'test'
